divak/__init__.py
divak/api.py
divak/internals.py
divak/testing.py
divak_tornado-0.0.3.dist-info/DESCRIPTION.rst
divak_tornado-0.0.3.dist-info/METADATA
divak_tornado-0.0.3.dist-info/RECORD
divak_tornado-0.0.3.dist-info/WHEEL
divak_tornado-0.0.3.dist-info/metadata.json
divak_tornado-0.0.3.dist-info/top_level.txt
