Metadata-Version: 2.0
Name: divak-tornado
Version: 0.0.3
Summary: Observe the behavior of your Tornado code
Home-page: https://github.com/dave-shawley/divak
Author: Dave Shawley
Author-email: daveshawley@gmail.com
License: BSD
Platform: UNKNOWN
Classifier: Intended Audience :: Developers
Classifier: License :: OSI Approved :: BSD License
Classifier: Operating System :: OS Independent
Classifier: Programming Language :: Python
Classifier: Programming Language :: Python :: 2
Classifier: Programming Language :: Python :: 2.7
Classifier: Programming Language :: Python :: 3
Classifier: Programming Language :: Python :: 3.4
Classifier: Programming Language :: Python :: 3.5
Classifier: Programming Language :: Python :: 3.6
Classifier: Development Status :: 2 - Pre-Alpha
Classifier: Environment :: Web Environment
Classifier: Topic :: Internet :: WWW/HTTP
Requires-Dist: tornado (<5,>=4.2)
